{"data_type":"unemployment","gender":"men","race":"latino","data":{"25025000100":{"unemployment_percent":6.787330316742081,"margin_of_error_percent":10.407239819004525,"unemployment_number":15,"margin_of_error_number":23,"total_samples":221,"certainty_ratio":0.6521739130434783},"25025000201":{"unemployment_percent":7.741935483870968,"margin_of_error_percent":17.419354838709676,"unemployment_number":12,"margin_of_error_number":27,"total_samples":155,"certainty_ratio":0.4444444444444444},"25025000202":{"unemployment_percent":20.535714285714285,"margin_of_error_percent":25.0,"unemployment_number":46,"margin_of_error_number":56,"total_samples":224,"certainty_ratio":0.8214285714285714},"25025000301":{"unemployment_percent":0.0,"margin_of_error_percent":4.615384615384616,"unemployment_number":0,"margin_of_error_number":12,"total_samples":260,"certainty_ratio":0.0},"25025000302":{"unemployment_percent":0.0,"margin_of_error_percent":11.009174311926607,"unemployment_number":0,"margin_of_error_number":12,"total_samples":109,"certainty_ratio":0.0},"25025000401":{"unemployment_percent":0.0,"margin_of_error_percent":8.333333333333332,"unemployment_number":0,"margin_of_error_number":17,"total_samples":204,"certainty_ratio":0.0},"25025000402":{"unemployment_percent":0.0,"margin_of_error_percent":10.714285714285714,"unemployment_number":0,"margin_of_error_number":12,"total_samples":112,"certainty_ratio":0.0},"25025000502":{"unemployment_percent":0.0,"margin_of_error_percent":12.408759124087592,"unemployment_number":0,"margin_of_error_number":17,"total_samples":137,"certainty_ratio":0.0},"25025000503":{"unemployment_percent":0.0,"margin_of_error_percent":26.666666666666668,"unemployment_number":0,"margin_of_error_number":12,"total_samples":45,"certainty_ratio":0.0},"25025000504":{"unemployment_percent":0.0,"margin_of_error_percent":18.75,"unemployment_number":0,"margin_of_error_number":12,"total_samples":64,"certainty_ratio":0.0},"25025000601":{"unemployment_percent":0.0,"margin_of_error_percent":11.881188118811881,"unemployment_number":0,"margin_of_error_number":12,"total_samples":101,"certainty_ratio":0.0},"25025000602":{"unemployment_percent":0.0,"margin_of_error_percent":6.0606060606060606,"unemployment_number":0,"margin_of_error_number":12,"total_samples":198,"certainty_ratio":0.0},"25025000701":{"unemployment_percent":2.0,"margin_of_error_percent":4.0,"unemployment_number":2,"margin_of_error_number":4,"total_samples":100,"certainty_ratio":0.5},"25025000703":{"unemployment_percent":13.286713286713287,"margin_of_error_percent":21.678321678321677,"unemployment_number":19,"margin_of_error_number":31,"total_samples":143,"certainty_ratio":0.6129032258064516},"25025000704":{"unemployment_percent":0.0,"margin_of_error_percent":37.5,"unemployment_number":0,"margin_of_error_number":12,"total_samples":32,"certainty_ratio":0.0},"25025000802":{"unemployment_percent":2.5380710659898478,"margin_of_error_percent":5.32994923857868,"unemployment_number":10,"margin_of_error_number":21,"total_samples":394,"certainty_ratio":0.47619047619047616},"25025000803":{"unemployment_percent":0.0,"margin_of_error_percent":16.50485436893204,"unemployment_number":0,"margin_of_error_number":17,"total_samples":103,"certainty_ratio":0.0},"25025010103":{"unemployment_percent":9.30232558139535,"margin_of_error_percent":13.953488372093023,"unemployment_number":12,"margin_of_error_number":18,"total_samples":129,"certainty_ratio":0.6666666666666666},"25025010104":{"unemployment_percent":3.361344537815126,"margin_of_error_percent":6.722689075630252,"unemployment_number":4,"margin_of_error_number":8,"total_samples":119,"certainty_ratio":0.5},"25025010203":{"unemployment_percent":0.0,"margin_of_error_percent":7.727272727272727,"unemployment_number":0,"margin_of_error_number":17,"total_samples":220,"certainty_ratio":0.0},"25025010204":{"unemployment_percent":26.25,"margin_of_error_percent":30.0,"unemployment_number":21,"margin_of_error_number":24,"total_samples":80,"certainty_ratio":0.875},"25025010300":{"unemployment_percent":0.0,"margin_of_error_percent":60.71428571428571,"unemployment_number":0,"margin_of_error_number":17,"total_samples":28,"certainty_ratio":0.0},"25025010403":{"unemployment_percent":15.42056074766355,"margin_of_error_percent":5.607476635514018,"unemployment_number":33,"margin_of_error_number":12,"total_samples":214,"certainty_ratio":2.75},"25025010404":{"unemployment_percent":25.925925925925924,"margin_of_error_percent":30.864197530864196,"unemployment_number":21,"margin_of_error_number":25,"total_samples":81,"certainty_ratio":0.84},"25025010405":{"unemployment_percent":17.365269461077844,"margin_of_error_percent":14.37125748502994,"unemployment_number":29,"margin_of_error_number":24,"total_samples":167,"certainty_ratio":1.2083333333333333},"25025010408":{"unemployment_percent":0.0,"margin_of_error_percent":25.0,"unemployment_number":0,"margin_of_error_number":12,"total_samples":48,"certainty_ratio":0.0},"25025010500":{"unemployment_percent":0.0,"margin_of_error_percent":6.557377049180328,"unemployment_number":0,"margin_of_error_number":12,"total_samples":183,"certainty_ratio":0.0},"25025010600":{"unemployment_percent":0.0,"margin_of_error_percent":0.0,"unemployment_number":0,"margin_of_error_number":12,"total_samples":0,"certainty_ratio":0.0},"25025010701":{"unemployment_percent":13.513513513513514,"margin_of_error_percent":22.972972972972975,"unemployment_number":10,"margin_of_error_number":17,"total_samples":74,"certainty_ratio":0.5882352941176471},"25025010702":{"unemployment_percent":0.0,"margin_of_error_percent":12.244897959183673,"unemployment_number":0,"margin_of_error_number":12,"total_samples":98,"certainty_ratio":0.0},"25025010801":{"unemployment_percent":0.0,"margin_of_error_percent":13.636363636363635,"unemployment_number":0,"margin_of_error_number":12,"total_samples":88,"certainty_ratio":0.0},"25025010802":{"unemployment_percent":20.945945945945947,"margin_of_error_percent":31.08108108108108,"unemployment_number":31,"margin_of_error_number":46,"total_samples":148,"certainty_ratio":0.6739130434782609},"25025020101":{"unemployment_percent":0.0,"margin_of_error_percent":5.970149253731343,"unemployment_number":0,"margin_of_error_number":12,"total_samples":201,"certainty_ratio":0.0},"25025020200":{"unemployment_percent":0.0,"margin_of_error_percent":13.043478260869565,"unemployment_number":0,"margin_of_error_number":12,"total_samples":92,"certainty_ratio":0.0},"25025020301":{"unemployment_percent":0.6993006993006993,"margin_of_error_percent":1.3986013986013985,"unemployment_number":1,"margin_of_error_number":2,"total_samples":143,"certainty_ratio":0.5},"25025020302":{"unemployment_percent":0.0,"margin_of_error_percent":60.0,"unemployment_number":0,"margin_of_error_number":12,"total_samples":20,"certainty_ratio":0.0},"25025020303":{"unemployment_percent":0.0,"margin_of_error_percent":23.076923076923077,"unemployment_number":0,"margin_of_error_number":12,"total_samples":52,"certainty_ratio":0.0},"25025030100":{"unemployment_percent":0.0,"margin_of_error_percent":12.0,"unemployment_number":0,"margin_of_error_number":12,"total_samples":100,"certainty_ratio":0.0},"25025030200":{"unemployment_percent":0.0,"margin_of_error_percent":37.5,"unemployment_number":0,"margin_of_error_number":12,"total_samples":32,"certainty_ratio":0.0},"25025030300":{"unemployment_percent":78.94736842105263,"margin_of_error_percent":110.5263157894737,"unemployment_number":60,"margin_of_error_number":84,"total_samples":76,"certainty_ratio":0.7142857142857143},"25025030400":{"unemployment_percent":0.0,"margin_of_error_percent":22.22222222222222,"unemployment_number":0,"margin_of_error_number":12,"total_samples":54,"certainty_ratio":0.0},"25025030500":{"unemployment_percent":0.0,"margin_of_error_percent":18.461538461538463,"unemployment_number":0,"margin_of_error_number":12,"total_samples":65,"certainty_ratio":0.0},"25025040100":{"unemployment_percent":0.0,"margin_of_error_percent":0.0,"unemployment_number":0,"margin_of_error_number":12,"total_samples":0,"certainty_ratio":0.0},"25025040200":{"unemployment_percent":19.047619047619047,"margin_of_error_percent":28.57142857142857,"unemployment_number":8,"margin_of_error_number":12,"total_samples":42,"certainty_ratio":0.6666666666666666},"25025040300":{"unemployment_percent":0.0,"margin_of_error_percent":17.91044776119403,"unemployment_number":0,"margin_of_error_number":12,"total_samples":67,"certainty_ratio":0.0},"25025040401":{"unemployment_percent":0.0,"margin_of_error_percent":12.631578947368421,"unemployment_number":0,"margin_of_error_number":12,"total_samples":95,"certainty_ratio":0.0},"25025040600":{"unemployment_percent":0.0,"margin_of_error_percent":15.789473684210526,"unemployment_number":0,"margin_of_error_number":12,"total_samples":76,"certainty_ratio":0.0},"25025040801":{"unemployment_percent":0.0,"margin_of_error_percent":11.76470588235294,"unemployment_number":0,"margin_of_error_number":12,"total_samples":102,"certainty_ratio":0.0},"25025050101":{"unemployment_percent":10.060189165950128,"margin_of_error_percent":7.738607050730868,"unemployment_number":117,"margin_of_error_number":90,"total_samples":1163,"certainty_ratio":1.3},"25025050200":{"unemployment_percent":0.0,"margin_of_error_percent":1.057871810827629,"unemployment_number":0,"margin_of_error_number":17,"total_samples":1607,"certainty_ratio":0.0},"25025050300":{"unemployment_percent":0.0,"margin_of_error_percent":5.128205128205128,"unemployment_number":0,"margin_of_error_number":12,"total_samples":234,"certainty_ratio":0.0},"25025050400":{"unemployment_percent":2.622950819672131,"margin_of_error_percent":4.2622950819672125,"unemployment_number":16,"margin_of_error_number":26,"total_samples":610,"certainty_ratio":0.6153846153846154},"25025050500":{"unemployment_percent":0.0,"margin_of_error_percent":2.941176470588235,"unemployment_number":0,"margin_of_error_number":12,"total_samples":408,"certainty_ratio":0.0},"25025050600":{"unemployment_percent":0.9749303621169917,"margin_of_error_percent":1.8105849582172702,"unemployment_number":7,"margin_of_error_number":13,"total_samples":718,"certainty_ratio":0.5384615384615384},"25025050700":{"unemployment_percent":3.3216783216783217,"margin_of_error_percent":4.778554778554779,"unemployment_number":57,"margin_of_error_number":82,"total_samples":1716,"certainty_ratio":0.6951219512195121},"25025050901":{"unemployment_percent":12.717770034843207,"margin_of_error_percent":9.843205574912892,"unemployment_number":146,"margin_of_error_number":113,"total_samples":1148,"certainty_ratio":1.2920353982300885},"25025051000":{"unemployment_percent":0.0,"margin_of_error_percent":2.4896265560165975,"unemployment_number":0,"margin_of_error_number":12,"total_samples":482,"certainty_ratio":0.0},"25025051101":{"unemployment_percent":10.324675324675326,"margin_of_error_percent":7.857142857142857,"unemployment_number":159,"margin_of_error_number":121,"total_samples":1540,"certainty_ratio":1.3140495867768596},"25025051200":{"unemployment_percent":3.5634743875278394,"margin_of_error_percent":5.3452115812917596,"unemployment_number":16,"margin_of_error_number":24,"total_samples":449,"certainty_ratio":0.6666666666666666},"25025060101":{"unemployment_percent":0.0,"margin_of_error_percent":50.0,"unemployment_number":0,"margin_of_error_number":12,"total_samples":24,"certainty_ratio":0.0},"25025060200":{"unemployment_percent":0.0,"margin_of_error_percent":75.0,"unemployment_number":0,"margin_of_error_number":12,"total_samples":16,"certainty_ratio":0.0},"25025060301":{"unemployment_percent":0.0,"margin_of_error_percent":15.789473684210526,"unemployment_number":0,"margin_of_error_number":12,"total_samples":76,"certainty_ratio":0.0},"25025060400":{"unemployment_percent":0.0,"margin_of_error_percent":56.666666666666664,"unemployment_number":0,"margin_of_error_number":17,"total_samples":30,"certainty_ratio":0.0},"25025060501":{"unemployment_percent":18.6046511627907,"margin_of_error_percent":30.813953488372093,"unemployment_number":32,"margin_of_error_number":53,"total_samples":172,"certainty_ratio":0.6037735849056604},"25025060600":{"unemployment_percent":8.333333333333332,"margin_of_error_percent":16.666666666666664,"unemployment_number":2,"margin_of_error_number":4,"total_samples":24,"certainty_ratio":0.5},"25025060700":{"unemployment_percent":0.0,"margin_of_error_percent":10.256410256410255,"unemployment_number":0,"margin_of_error_number":12,"total_samples":117,"certainty_ratio":0.0},"25025060800":{"unemployment_percent":0.0,"margin_of_error_percent":0.0,"unemployment_number":0,"margin_of_error_number":12,"total_samples":0,"certainty_ratio":0.0},"25025061000":{"unemployment_percent":20.24793388429752,"margin_of_error_percent":29.338842975206614,"unemployment_number":49,"margin_of_error_number":71,"total_samples":242,"certainty_ratio":0.6901408450704225},"25025061101":{"unemployment_percent":8.73015873015873,"margin_of_error_percent":13.492063492063492,"unemployment_number":11,"margin_of_error_number":17,"total_samples":126,"certainty_ratio":0.6470588235294118},"25025061200":{"unemployment_percent":0.0,"margin_of_error_percent":5.853658536585367,"unemployment_number":0,"margin_of_error_number":12,"total_samples":205,"certainty_ratio":0.0},"25025070101":{"unemployment_percent":11.737089201877934,"margin_of_error_percent":21.5962441314554,"unemployment_number":25,"margin_of_error_number":46,"total_samples":213,"certainty_ratio":0.5434782608695652},"25025070200":{"unemployment_percent":42.857142857142854,"margin_of_error_percent":89.28571428571429,"unemployment_number":12,"margin_of_error_number":25,"total_samples":28,"certainty_ratio":0.48},"25025070300":{"unemployment_percent":0.0,"margin_of_error_percent":5.405405405405405,"unemployment_number":0,"margin_of_error_number":12,"total_samples":222,"certainty_ratio":0.0},"25025070402":{"unemployment_percent":0.0,"margin_of_error_percent":28.57142857142857,"unemployment_number":0,"margin_of_error_number":12,"total_samples":42,"certainty_ratio":0.0},"25025070500":{"unemployment_percent":44.951140065146575,"margin_of_error_percent":24.104234527687296,"unemployment_number":138,"margin_of_error_number":74,"total_samples":307,"certainty_ratio":1.864864864864865},"25025070600":{"unemployment_percent":0.0,"margin_of_error_percent":15.584415584415584,"unemployment_number":0,"margin_of_error_number":12,"total_samples":77,"certainty_ratio":0.0},"25025070700":{"unemployment_percent":0.0,"margin_of_error_percent":12.76595744680851,"unemployment_number":0,"margin_of_error_number":12,"total_samples":94,"certainty_ratio":0.0},"25025070800":{"unemployment_percent":0.0,"margin_of_error_percent":9.75609756097561,"unemployment_number":0,"margin_of_error_number":12,"total_samples":123,"certainty_ratio":0.0},"25025070900":{"unemployment_percent":0.0,"margin_of_error_percent":46.15384615384615,"unemployment_number":0,"margin_of_error_number":12,"total_samples":26,"certainty_ratio":0.0},"25025071101":{"unemployment_percent":10.344827586206897,"margin_of_error_percent":24.137931034482758,"unemployment_number":6,"margin_of_error_number":14,"total_samples":58,"certainty_ratio":0.42857142857142855},"25025071201":{"unemployment_percent":16.7420814479638,"margin_of_error_percent":17.647058823529413,"unemployment_number":37,"margin_of_error_number":39,"total_samples":221,"certainty_ratio":0.9487179487179487},"25025080100":{"unemployment_percent":39.189189189189186,"margin_of_error_percent":36.486486486486484,"unemployment_number":29,"margin_of_error_number":27,"total_samples":74,"certainty_ratio":1.0740740740740742},"25025080300":{"unemployment_percent":5.952380952380952,"margin_of_error_percent":14.285714285714285,"unemployment_number":5,"margin_of_error_number":12,"total_samples":84,"certainty_ratio":0.4166666666666667},"25025080401":{"unemployment_percent":0.0,"margin_of_error_percent":8.955223880597014,"unemployment_number":0,"margin_of_error_number":12,"total_samples":134,"certainty_ratio":0.0},"25025080500":{"unemployment_percent":7.524271844660194,"margin_of_error_percent":7.038834951456311,"unemployment_number":31,"margin_of_error_number":29,"total_samples":412,"certainty_ratio":1.0689655172413792},"25025080601":{"unemployment_percent":49.152542372881356,"margin_of_error_percent":40.67796610169492,"unemployment_number":29,"margin_of_error_number":24,"total_samples":59,"certainty_ratio":1.2083333333333333},"25025080801":{"unemployment_percent":40.45584045584046,"margin_of_error_percent":24.216524216524217,"unemployment_number":142,"margin_of_error_number":85,"total_samples":351,"certainty_ratio":1.6705882352941177},"25025080900":{"unemployment_percent":0.0,"margin_of_error_percent":6.122448979591836,"unemployment_number":0,"margin_of_error_number":12,"total_samples":196,"certainty_ratio":0.0},"25025081001":{"unemployment_percent":8.670520231213873,"margin_of_error_percent":13.872832369942195,"unemployment_number":15,"margin_of_error_number":24,"total_samples":173,"certainty_ratio":0.625},"25025081100":{"unemployment_percent":45.56962025316456,"margin_of_error_percent":72.15189873417721,"unemployment_number":36,"margin_of_error_number":57,"total_samples":79,"certainty_ratio":0.631578947368421},"25025081200":{"unemployment_percent":0.0,"margin_of_error_percent":4.562737642585551,"unemployment_number":0,"margin_of_error_number":12,"total_samples":263,"certainty_ratio":0.0},"25025081300":{"unemployment_percent":0.0,"margin_of_error_percent":4.25531914893617,"unemployment_number":0,"margin_of_error_number":12,"total_samples":282,"certainty_ratio":0.0},"25025081400":{"unemployment_percent":0.0,"margin_of_error_percent":23.52941176470588,"unemployment_number":0,"margin_of_error_number":12,"total_samples":51,"certainty_ratio":0.0},"25025081500":{"unemployment_percent":33.83458646616541,"margin_of_error_percent":40.6015037593985,"unemployment_number":45,"margin_of_error_number":54,"total_samples":133,"certainty_ratio":0.8333333333333334},"25025081700":{"unemployment_percent":27.927927927927925,"margin_of_error_percent":26.126126126126124,"unemployment_number":62,"margin_of_error_number":58,"total_samples":222,"certainty_ratio":1.0689655172413792},"25025081800":{"unemployment_percent":12.592592592592592,"margin_of_error_percent":22.22222222222222,"unemployment_number":17,"margin_of_error_number":30,"total_samples":135,"certainty_ratio":0.5666666666666667},"25025081900":{"unemployment_percent":8.967391304347826,"margin_of_error_percent":14.402173913043478,"unemployment_number":33,"margin_of_error_number":53,"total_samples":368,"certainty_ratio":0.6226415094339622},"25025082000":{"unemployment_percent":12.389380530973451,"margin_of_error_percent":20.353982300884958,"unemployment_number":28,"margin_of_error_number":46,"total_samples":226,"certainty_ratio":0.6086956521739131},"25025082100":{"unemployment_percent":8.8339222614841,"margin_of_error_percent":16.607773851590103,"unemployment_number":25,"margin_of_error_number":47,"total_samples":283,"certainty_ratio":0.5319148936170213},"25025090100":{"unemployment_percent":3.278688524590164,"margin_of_error_percent":5.122950819672131,"unemployment_number":16,"margin_of_error_number":25,"total_samples":488,"certainty_ratio":0.64},"25025090200":{"unemployment_percent":12.871287128712872,"margin_of_error_percent":18.81188118811881,"unemployment_number":13,"margin_of_error_number":19,"total_samples":101,"certainty_ratio":0.6842105263157895},"25025090300":{"unemployment_percent":0.0,"margin_of_error_percent":5.5813953488372094,"unemployment_number":0,"margin_of_error_number":12,"total_samples":215,"certainty_ratio":0.0},"25025090400":{"unemployment_percent":15.961800818553886,"margin_of_error_percent":11.732605729877218,"unemployment_number":117,"margin_of_error_number":86,"total_samples":733,"certainty_ratio":1.3604651162790697},"25025090600":{"unemployment_percent":0.0,"margin_of_error_percent":13.48314606741573,"unemployment_number":0,"margin_of_error_number":12,"total_samples":89,"certainty_ratio":0.0},"25025090700":{"unemployment_percent":0.0,"margin_of_error_percent":13.043478260869565,"unemployment_number":0,"margin_of_error_number":12,"total_samples":92,"certainty_ratio":0.0},"25025090901":{"unemployment_percent":11.870503597122301,"margin_of_error_percent":13.309352517985612,"unemployment_number":33,"margin_of_error_number":37,"total_samples":278,"certainty_ratio":0.8918918918918919},"25025091001":{"unemployment_percent":0.0,"margin_of_error_percent":36.36363636363637,"unemployment_number":0,"margin_of_error_number":12,"total_samples":33,"certainty_ratio":0.0},"25025091100":{"unemployment_percent":7.766990291262135,"margin_of_error_percent":12.135922330097088,"unemployment_number":16,"margin_of_error_number":25,"total_samples":206,"certainty_ratio":0.64},"25025091200":{"unemployment_percent":0.0,"margin_of_error_percent":8.0,"unemployment_number":0,"margin_of_error_number":12,"total_samples":150,"certainty_ratio":0.0},"25025091300":{"unemployment_percent":0.0,"margin_of_error_percent":4.8979591836734695,"unemployment_number":0,"margin_of_error_number":12,"total_samples":245,"certainty_ratio":0.0},"25025091400":{"unemployment_percent":17.333333333333336,"margin_of_error_percent":14.222222222222221,"unemployment_number":39,"margin_of_error_number":32,"total_samples":225,"certainty_ratio":1.21875},"25025091500":{"unemployment_percent":18.181818181818183,"margin_of_error_percent":13.107822410147993,"unemployment_number":86,"margin_of_error_number":62,"total_samples":473,"certainty_ratio":1.3870967741935485},"25025091600":{"unemployment_percent":17.378048780487802,"margin_of_error_percent":17.682926829268293,"unemployment_number":57,"margin_of_error_number":58,"total_samples":328,"certainty_ratio":0.9827586206896551},"25025091700":{"unemployment_percent":12.82051282051282,"margin_of_error_percent":15.384615384615385,"unemployment_number":30,"margin_of_error_number":36,"total_samples":234,"certainty_ratio":0.8333333333333334},"25025091800":{"unemployment_percent":35.38461538461539,"margin_of_error_percent":30.76923076923077,"unemployment_number":138,"margin_of_error_number":120,"total_samples":390,"certainty_ratio":1.15},"25025091900":{"unemployment_percent":28.254847645429365,"margin_of_error_percent":23.26869806094183,"unemployment_number":102,"margin_of_error_number":84,"total_samples":361,"certainty_ratio":1.2142857142857142},"25025092000":{"unemployment_percent":7.435897435897436,"margin_of_error_percent":10.256410256410255,"unemployment_number":29,"margin_of_error_number":40,"total_samples":390,"certainty_ratio":0.725},"25025092101":{"unemployment_percent":0.0,"margin_of_error_percent":5.3627760252365935,"unemployment_number":0,"margin_of_error_number":17,"total_samples":317,"certainty_ratio":0.0},"25025092200":{"unemployment_percent":0.0,"margin_of_error_percent":9.090909090909092,"unemployment_number":0,"margin_of_error_number":12,"total_samples":132,"certainty_ratio":0.0},"25025092300":{"unemployment_percent":10.0,"margin_of_error_percent":8.695652173913043,"unemployment_number":23,"margin_of_error_number":20,"total_samples":230,"certainty_ratio":1.15},"25025092400":{"unemployment_percent":0.0,"margin_of_error_percent":8.415841584158416,"unemployment_number":0,"margin_of_error_number":17,"total_samples":202,"certainty_ratio":0.0},"25025100100":{"unemployment_percent":13.60544217687075,"margin_of_error_percent":21.08843537414966,"unemployment_number":20,"margin_of_error_number":31,"total_samples":147,"certainty_ratio":0.6451612903225806},"25025100200":{"unemployment_percent":0.0,"margin_of_error_percent":10.16949152542373,"unemployment_number":0,"margin_of_error_number":12,"total_samples":118,"certainty_ratio":0.0},"25025100300":{"unemployment_percent":38.333333333333336,"margin_of_error_percent":58.333333333333336,"unemployment_number":23,"margin_of_error_number":35,"total_samples":60,"certainty_ratio":0.6571428571428571},"25025100400":{"unemployment_percent":27.445652173913043,"margin_of_error_percent":31.25,"unemployment_number":101,"margin_of_error_number":115,"total_samples":368,"certainty_ratio":0.8782608695652174},"25025100500":{"unemployment_percent":1.1049723756906076,"margin_of_error_percent":2.209944751381215,"unemployment_number":2,"margin_of_error_number":4,"total_samples":181,"certainty_ratio":0.5},"25025100601":{"unemployment_percent":9.33852140077821,"margin_of_error_percent":14.785992217898833,"unemployment_number":24,"margin_of_error_number":38,"total_samples":257,"certainty_ratio":0.631578947368421},"25025100603":{"unemployment_percent":0.0,"margin_of_error_percent":66.66666666666666,"unemployment_number":0,"margin_of_error_number":12,"total_samples":18,"certainty_ratio":0.0},"25025100700":{"unemployment_percent":0.0,"margin_of_error_percent":100.0,"unemployment_number":0,"margin_of_error_number":12,"total_samples":12,"certainty_ratio":0.0},"25025100800":{"unemployment_percent":62.5,"margin_of_error_percent":100.0,"unemployment_number":50,"margin_of_error_number":80,"total_samples":80,"certainty_ratio":0.625},"25025100900":{"unemployment_percent":0.0,"margin_of_error_percent":5.5045871559633035,"unemployment_number":0,"margin_of_error_number":12,"total_samples":218,"certainty_ratio":0.0},"25025101001":{"unemployment_percent":18.857142857142858,"margin_of_error_percent":31.428571428571427,"unemployment_number":33,"margin_of_error_number":55,"total_samples":175,"certainty_ratio":0.6},"25025101002":{"unemployment_percent":0.0,"margin_of_error_percent":12.686567164179104,"unemployment_number":0,"margin_of_error_number":17,"total_samples":134,"certainty_ratio":0.0},"25025101101":{"unemployment_percent":56.470588235294116,"margin_of_error_percent":62.35294117647059,"unemployment_number":48,"margin_of_error_number":53,"total_samples":85,"certainty_ratio":0.9056603773584906},"25025101102":{"unemployment_percent":0.0,"margin_of_error_percent":37.77777777777778,"unemployment_number":0,"margin_of_error_number":17,"total_samples":45,"certainty_ratio":0.0},"25025110103":{"unemployment_percent":7.228915662650602,"margin_of_error_percent":11.244979919678714,"unemployment_number":18,"margin_of_error_number":28,"total_samples":249,"certainty_ratio":0.6428571428571429},"25025110201":{"unemployment_percent":0.0,"margin_of_error_percent":5.47945205479452,"unemployment_number":0,"margin_of_error_number":12,"total_samples":219,"certainty_ratio":0.0},"25025110301":{"unemployment_percent":0.0,"margin_of_error_percent":4.724409448818897,"unemployment_number":0,"margin_of_error_number":12,"total_samples":254,"certainty_ratio":0.0},"25025110401":{"unemployment_percent":15.137614678899084,"margin_of_error_percent":15.59633027522936,"unemployment_number":33,"margin_of_error_number":34,"total_samples":218,"certainty_ratio":0.9705882352941176},"25025110403":{"unemployment_percent":0.0,"margin_of_error_percent":4.137931034482759,"unemployment_number":0,"margin_of_error_number":12,"total_samples":290,"certainty_ratio":0.0},"25025110501":{"unemployment_percent":0.0,"margin_of_error_percent":17.391304347826086,"unemployment_number":0,"margin_of_error_number":12,"total_samples":69,"certainty_ratio":0.0},"25025110502":{"unemployment_percent":0.0,"margin_of_error_percent":2.2222222222222223,"unemployment_number":0,"margin_of_error_number":12,"total_samples":540,"certainty_ratio":0.0},"25025110601":{"unemployment_percent":18.181818181818183,"margin_of_error_percent":31.818181818181817,"unemployment_number":8,"margin_of_error_number":14,"total_samples":44,"certainty_ratio":0.5714285714285714},"25025110607":{"unemployment_percent":0.0,"margin_of_error_percent":9.239130434782608,"unemployment_number":0,"margin_of_error_number":17,"total_samples":184,"certainty_ratio":0.0},"25025120103":{"unemployment_percent":0.0,"margin_of_error_percent":19.672131147540984,"unemployment_number":0,"margin_of_error_number":12,"total_samples":61,"certainty_ratio":0.0},"25025120104":{"unemployment_percent":25.0,"margin_of_error_percent":42.857142857142854,"unemployment_number":14,"margin_of_error_number":24,"total_samples":56,"certainty_ratio":0.5833333333333334},"25025120105":{"unemployment_percent":18.51851851851852,"margin_of_error_percent":37.03703703703704,"unemployment_number":5,"margin_of_error_number":10,"total_samples":27,"certainty_ratio":0.5},"25025120201":{"unemployment_percent":13.818181818181818,"margin_of_error_percent":20.363636363636363,"unemployment_number":38,"margin_of_error_number":56,"total_samples":275,"certainty_ratio":0.6785714285714286},"25025120301":{"unemployment_percent":16.9811320754717,"margin_of_error_percent":14.675052410901468,"unemployment_number":81,"margin_of_error_number":70,"total_samples":477,"certainty_ratio":1.1571428571428573},"25025120400":{"unemployment_percent":0.0,"margin_of_error_percent":7.203389830508475,"unemployment_number":0,"margin_of_error_number":17,"total_samples":236,"certainty_ratio":0.0},"25025120500":{"unemployment_percent":18.373493975903614,"margin_of_error_percent":15.66265060240964,"unemployment_number":61,"margin_of_error_number":52,"total_samples":332,"certainty_ratio":1.1730769230769231},"25025120600":{"unemployment_percent":0.0,"margin_of_error_percent":3.8095238095238098,"unemployment_number":0,"margin_of_error_number":12,"total_samples":315,"certainty_ratio":0.0},"25025120700":{"unemployment_percent":21.341463414634145,"margin_of_error_percent":28.65853658536585,"unemployment_number":35,"margin_of_error_number":47,"total_samples":164,"certainty_ratio":0.7446808510638298},"25025130100":{"unemployment_percent":0.0,"margin_of_error_percent":31.48148148148148,"unemployment_number":0,"margin_of_error_number":17,"total_samples":54,"certainty_ratio":0.0},"25025130200":{"unemployment_percent":17.46031746031746,"margin_of_error_percent":28.57142857142857,"unemployment_number":11,"margin_of_error_number":18,"total_samples":63,"certainty_ratio":0.6111111111111112},"25025130300":{"unemployment_percent":0.0,"margin_of_error_percent":16.216216216216218,"unemployment_number":0,"margin_of_error_number":12,"total_samples":74,"certainty_ratio":0.0},"25025130402":{"unemployment_percent":0.0,"margin_of_error_percent":14.814814814814813,"unemployment_number":0,"margin_of_error_number":12,"total_samples":81,"certainty_ratio":0.0},"25025130404":{"unemployment_percent":0.0,"margin_of_error_percent":12.76595744680851,"unemployment_number":0,"margin_of_error_number":12,"total_samples":94,"certainty_ratio":0.0},"25025130406":{"unemployment_percent":10.163934426229508,"margin_of_error_percent":14.754098360655737,"unemployment_number":31,"margin_of_error_number":45,"total_samples":305,"certainty_ratio":0.6888888888888889},"25025140102":{"unemployment_percent":11.730205278592376,"margin_of_error_percent":11.143695014662756,"unemployment_number":40,"margin_of_error_number":38,"total_samples":341,"certainty_ratio":1.0526315789473684},"25025140105":{"unemployment_percent":6.695464362850973,"margin_of_error_percent":7.343412526997841,"unemployment_number":31,"margin_of_error_number":34,"total_samples":463,"certainty_ratio":0.9117647058823529},"25025140106":{"unemployment_percent":11.214953271028037,"margin_of_error_percent":19.626168224299064,"unemployment_number":12,"margin_of_error_number":21,"total_samples":107,"certainty_ratio":0.5714285714285714},"25025140107":{"unemployment_percent":0.0,"margin_of_error_percent":6.091370558375635,"unemployment_number":0,"margin_of_error_number":12,"total_samples":197,"certainty_ratio":0.0},"25025140201":{"unemployment_percent":0.0,"margin_of_error_percent":8.391608391608392,"unemployment_number":0,"margin_of_error_number":12,"total_samples":143,"certainty_ratio":0.0},"25025140202":{"unemployment_percent":0.0,"margin_of_error_percent":2.8052805280528053,"unemployment_number":0,"margin_of_error_number":17,"total_samples":606,"certainty_ratio":0.0},"25025140300":{"unemployment_percent":4.6255506607929515,"margin_of_error_percent":7.929515418502203,"unemployment_number":21,"margin_of_error_number":36,"total_samples":454,"certainty_ratio":0.5833333333333334},"25025140400":{"unemployment_percent":0.0,"margin_of_error_percent":3.2442748091603053,"unemployment_number":0,"margin_of_error_number":17,"total_samples":524,"certainty_ratio":0.0},"25025160101":{"unemployment_percent":7.203579418344519,"margin_of_error_percent":6.621923937360179,"unemployment_number":161,"margin_of_error_number":148,"total_samples":2235,"certainty_ratio":1.087837837837838},"25025160200":{"unemployment_percent":3.4611786716557527,"margin_of_error_percent":3.7418147801683816,"unemployment_number":37,"margin_of_error_number":40,"total_samples":1069,"certainty_ratio":0.925},"25025160300":{"unemployment_percent":0.0,"margin_of_error_percent":7.5,"unemployment_number":0,"margin_of_error_number":12,"total_samples":160,"certainty_ratio":0.0},"25025160400":{"unemployment_percent":6.340819022457067,"margin_of_error_percent":7.001321003963012,"unemployment_number":48,"margin_of_error_number":53,"total_samples":757,"certainty_ratio":0.9056603773584906},"25025160501":{"unemployment_percent":7.865168539325842,"margin_of_error_percent":9.213483146067416,"unemployment_number":105,"margin_of_error_number":123,"total_samples":1335,"certainty_ratio":0.8536585365853658},"25025160502":{"unemployment_percent":3.722334004024145,"margin_of_error_percent":3.6217303822937628,"unemployment_number":37,"margin_of_error_number":36,"total_samples":994,"certainty_ratio":1.0277777777777777},"25025160601":{"unemployment_percent":7.530864197530865,"margin_of_error_percent":8.148148148148149,"unemployment_number":61,"margin_of_error_number":66,"total_samples":810,"certainty_ratio":0.9242424242424242},"25025160602":{"unemployment_percent":0.0,"margin_of_error_percent":2.263648468708389,"unemployment_number":0,"margin_of_error_number":17,"total_samples":751,"certainty_ratio":0.0},"25025170100":{"unemployment_percent":15.581643543223054,"margin_of_error_percent":14.941302027748133,"unemployment_number":146,"margin_of_error_number":140,"total_samples":937,"certainty_ratio":1.042857142857143},"25025170200":{"unemployment_percent":0.0,"margin_of_error_percent":3.64741641337386,"unemployment_number":0,"margin_of_error_number":12,"total_samples":329,"certainty_ratio":0.0},"25025170300":{"unemployment_percent":1.545595054095827,"margin_of_error_percent":2.936630602782071,"unemployment_number":10,"margin_of_error_number":19,"total_samples":647,"certainty_ratio":0.5263157894736842},"25025170400":{"unemployment_percent":2.6272577996715927,"margin_of_error_percent":4.926108374384237,"unemployment_number":16,"margin_of_error_number":30,"total_samples":609,"certainty_ratio":0.5333333333333333},"25025170501":{"unemployment_percent":15.370705244122965,"margin_of_error_percent":17.17902350813743,"unemployment_number":85,"margin_of_error_number":95,"total_samples":553,"certainty_ratio":0.8947368421052632},"25025170502":{"unemployment_percent":34.84848484848485,"margin_of_error_percent":60.60606060606061,"unemployment_number":23,"margin_of_error_number":40,"total_samples":66,"certainty_ratio":0.575},"25025170601":{"unemployment_percent":0.0,"margin_of_error_percent":2.2309711286089238,"unemployment_number":0,"margin_of_error_number":17,"total_samples":762,"certainty_ratio":0.0},"25025170701":{"unemployment_percent":4.929577464788732,"margin_of_error_percent":7.394366197183098,"unemployment_number":14,"margin_of_error_number":21,"total_samples":284,"certainty_ratio":0.6666666666666666},"25025170702":{"unemployment_percent":3.027754415475189,"margin_of_error_percent":3.616484440706476,"unemployment_number":36,"margin_of_error_number":43,"total_samples":1189,"certainty_ratio":0.8372093023255814},"25025170800":{"unemployment_percent":1.7543859649122806,"margin_of_error_percent":3.199174406604747,"unemployment_number":17,"margin_of_error_number":31,"total_samples":969,"certainty_ratio":0.5483870967741935},"25025180101":{"unemployment_percent":0.0,"margin_of_error_percent":7.5,"unemployment_number":0,"margin_of_error_number":12,"total_samples":160,"certainty_ratio":0.0},"25025180200":{"unemployment_percent":0.0,"margin_of_error_percent":6.779661016949152,"unemployment_number":0,"margin_of_error_number":12,"total_samples":177,"certainty_ratio":0.0},"25025180301":{"unemployment_percent":0.0,"margin_of_error_percent":14.457831325301203,"unemployment_number":0,"margin_of_error_number":12,"total_samples":83,"certainty_ratio":0.0},"25025180400":{"unemployment_percent":0.0,"margin_of_error_percent":9.75609756097561,"unemployment_number":0,"margin_of_error_number":12,"total_samples":123,"certainty_ratio":0.0},"25025180500":{"unemployment_percent":0.0,"margin_of_error_percent":38.70967741935484,"unemployment_number":0,"margin_of_error_number":12,"total_samples":31,"certainty_ratio":0.0},"25025980101":{"unemployment_percent":72.54901960784314,"margin_of_error_percent":168.62745098039215,"unemployment_number":37,"margin_of_error_number":86,"total_samples":51,"certainty_ratio":0.43023255813953487},"25025980300":{"unemployment_percent":42.857142857142854,"margin_of_error_percent":100.0,"unemployment_number":15,"margin_of_error_number":35,"total_samples":35,"certainty_ratio":0.42857142857142855},"25025980700":{"unemployment_percent":0.0,"margin_of_error_percent":0.0,"unemployment_number":0,"margin_of_error_number":12,"total_samples":0,"certainty_ratio":0.0},"25025981000":{"unemployment_percent":0.0,"margin_of_error_percent":0.0,"unemployment_number":0,"margin_of_error_number":12,"total_samples":0,"certainty_ratio":0.0},"25025981100":{"unemployment_percent":0.0,"margin_of_error_percent":0.0,"unemployment_number":0,"margin_of_error_number":12,"total_samples":0,"certainty_ratio":0.0},"25025981201":{"unemployment_percent":0.0,"margin_of_error_percent":0.0,"unemployment_number":0,"margin_of_error_number":12,"total_samples":0,"certainty_ratio":0.0},"25025981202":{"unemployment_percent":0.0,"margin_of_error_percent":0.0,"unemployment_number":0,"margin_of_error_number":12,"total_samples":0,"certainty_ratio":0.0},"25025981300":{"unemployment_percent":0.0,"margin_of_error_percent":26.08695652173913,"unemployment_number":0,"margin_of_error_number":12,"total_samples":46,"certainty_ratio":0.0},"25025981501":{"unemployment_percent":0.0,"margin_of_error_percent":0.0,"unemployment_number":0,"margin_of_error_number":12,"total_samples":0,"certainty_ratio":0.0},"25025981502":{"unemployment_percent":0.0,"margin_of_error_percent":0.0,"unemployment_number":0,"margin_of_error_number":12,"total_samples":0,"certainty_ratio":0.0},"25025981600":{"unemployment_percent":0.0,"margin_of_error_percent":0.0,"unemployment_number":0,"margin_of_error_number":12,"total_samples":0,"certainty_ratio":0.0},"25025981700":{"unemployment_percent":0.0,"margin_of_error_percent":0.0,"unemployment_number":0,"margin_of_error_number":12,"total_samples":0,"certainty_ratio":0.0},"25025981800":{"unemployment_percent":0.0,"margin_of_error_percent":0.0,"unemployment_number":0,"margin_of_error_number":12,"total_samples":0,"certainty_ratio":0.0},"25025990101":{"unemployment_percent":0.0,"margin_of_error_percent":21.818181818181817,"unemployment_number":0,"margin_of_error_number":12,"total_samples":55,"certainty_ratio":0.0}}}