{"data_type":"unemployment","gender":"men","race":"black","data":{"25025000100":{"unemployment_percent":0.0,"margin_of_error_percent":23.61111111111111,"unemployment_number":0,"margin_of_error_number":17,"total_samples":72,"certainty_ratio":0.0},"25025000201":{"unemployment_percent":0.0,"margin_of_error_percent":27.906976744186046,"unemployment_number":0,"margin_of_error_number":12,"total_samples":43,"certainty_ratio":0.0},"25025000202":{"unemployment_percent":41.66666666666667,"margin_of_error_percent":63.888888888888886,"unemployment_number":15,"margin_of_error_number":23,"total_samples":36,"certainty_ratio":0.6521739130434783},"25025000301":{"unemployment_percent":0.0,"margin_of_error_percent":7.643312101910828,"unemployment_number":0,"margin_of_error_number":12,"total_samples":157,"certainty_ratio":0.0},"25025000302":{"unemployment_percent":0.0,"margin_of_error_percent":17.142857142857142,"unemployment_number":0,"margin_of_error_number":12,"total_samples":70,"certainty_ratio":0.0},"25025000401":{"unemployment_percent":0.0,"margin_of_error_percent":16.666666666666664,"unemployment_number":0,"margin_of_error_number":17,"total_samples":102,"certainty_ratio":0.0},"25025000402":{"unemployment_percent":0.0,"margin_of_error_percent":85.71428571428571,"unemployment_number":0,"margin_of_error_number":12,"total_samples":14,"certainty_ratio":0.0},"25025000502":{"unemployment_percent":0.0,"margin_of_error_percent":0.0,"unemployment_number":0,"margin_of_error_number":17,"total_samples":0,"certainty_ratio":0.0},"25025000503":{"unemployment_percent":0.0,"margin_of_error_percent":70.58823529411765,"unemployment_number":0,"margin_of_error_number":12,"total_samples":17,"certainty_ratio":0.0},"25025000504":{"unemployment_percent":0.0,"margin_of_error_percent":0.0,"unemployment_number":0,"margin_of_error_number":12,"total_samples":0,"certainty_ratio":0.0},"25025000601":{"unemployment_percent":19.565217391304348,"margin_of_error_percent":28.26086956521739,"unemployment_number":9,"margin_of_error_number":13,"total_samples":46,"certainty_ratio":0.6923076923076923},"25025000602":{"unemployment_percent":0.0,"margin_of_error_percent":46.15384615384615,"unemployment_number":0,"margin_of_error_number":12,"total_samples":26,"certainty_ratio":0.0},"25025000701":{"unemployment_percent":0.0,"margin_of_error_percent":3.934426229508197,"unemployment_number":0,"margin_of_error_number":12,"total_samples":305,"certainty_ratio":0.0},"25025000703":{"unemployment_percent":0.0,"margin_of_error_percent":36.36363636363637,"unemployment_number":0,"margin_of_error_number":12,"total_samples":33,"certainty_ratio":0.0},"25025000704":{"unemployment_percent":0.0,"margin_of_error_percent":8.695652173913043,"unemployment_number":0,"margin_of_error_number":12,"total_samples":138,"certainty_ratio":0.0},"25025000802":{"unemployment_percent":6.134969325153374,"margin_of_error_percent":12.883435582822086,"unemployment_number":10,"margin_of_error_number":21,"total_samples":163,"certainty_ratio":0.47619047619047616},"25025000803":{"unemployment_percent":14.285714285714285,"margin_of_error_percent":31.428571428571427,"unemployment_number":10,"margin_of_error_number":22,"total_samples":70,"certainty_ratio":0.45454545454545453},"25025010103":{"unemployment_percent":3.8461538461538463,"margin_of_error_percent":15.384615384615385,"unemployment_number":2,"margin_of_error_number":8,"total_samples":52,"certainty_ratio":0.25},"25025010104":{"unemployment_percent":0.0,"margin_of_error_percent":130.76923076923077,"unemployment_number":0,"margin_of_error_number":17,"total_samples":13,"certainty_ratio":0.0},"25025010203":{"unemployment_percent":0.0,"margin_of_error_percent":10.69182389937107,"unemployment_number":0,"margin_of_error_number":17,"total_samples":159,"certainty_ratio":0.0},"25025010204":{"unemployment_percent":0.0,"margin_of_error_percent":52.17391304347826,"unemployment_number":0,"margin_of_error_number":12,"total_samples":23,"certainty_ratio":0.0},"25025010300":{"unemployment_percent":10.909090909090908,"margin_of_error_percent":12.727272727272727,"unemployment_number":6,"margin_of_error_number":7,"total_samples":55,"certainty_ratio":0.8571428571428571},"25025010403":{"unemployment_percent":100.0,"margin_of_error_percent":73.33333333333333,"unemployment_number":60,"margin_of_error_number":44,"total_samples":60,"certainty_ratio":1.3636363636363635},"25025010404":{"unemployment_percent":0.0,"margin_of_error_percent":73.91304347826086,"unemployment_number":0,"margin_of_error_number":17,"total_samples":23,"certainty_ratio":0.0},"25025010405":{"unemployment_percent":29.78723404255319,"margin_of_error_percent":29.078014184397162,"unemployment_number":42,"margin_of_error_number":41,"total_samples":141,"certainty_ratio":1.024390243902439},"25025010408":{"unemployment_percent":20.0,"margin_of_error_percent":32.30769230769231,"unemployment_number":13,"margin_of_error_number":21,"total_samples":65,"certainty_ratio":0.6190476190476191},"25025010500":{"unemployment_percent":27.142857142857142,"margin_of_error_percent":37.142857142857146,"unemployment_number":19,"margin_of_error_number":26,"total_samples":70,"certainty_ratio":0.7307692307692307},"25025010600":{"unemployment_percent":0.0,"margin_of_error_percent":28.57142857142857,"unemployment_number":0,"margin_of_error_number":12,"total_samples":42,"certainty_ratio":0.0},"25025010701":{"unemployment_percent":2.857142857142857,"margin_of_error_percent":11.428571428571429,"unemployment_number":1,"margin_of_error_number":4,"total_samples":35,"certainty_ratio":0.25},"25025010702":{"unemployment_percent":100.0,"margin_of_error_percent":183.33333333333331,"unemployment_number":6,"margin_of_error_number":11,"total_samples":6,"certainty_ratio":0.5454545454545454},"25025010801":{"unemployment_percent":0.0,"margin_of_error_percent":22.641509433962266,"unemployment_number":0,"margin_of_error_number":12,"total_samples":53,"certainty_ratio":0.0},"25025010802":{"unemployment_percent":0.0,"margin_of_error_percent":0.0,"unemployment_number":0,"margin_of_error_number":12,"total_samples":0,"certainty_ratio":0.0},"25025020101":{"unemployment_percent":0.0,"margin_of_error_percent":22.22222222222222,"unemployment_number":0,"margin_of_error_number":12,"total_samples":54,"certainty_ratio":0.0},"25025020200":{"unemployment_percent":0.0,"margin_of_error_percent":0.0,"unemployment_number":0,"margin_of_error_number":12,"total_samples":0,"certainty_ratio":0.0},"25025020301":{"unemployment_percent":8.333333333333332,"margin_of_error_percent":16.666666666666664,"unemployment_number":1,"margin_of_error_number":2,"total_samples":12,"certainty_ratio":0.5},"25025020302":{"unemployment_percent":0.0,"margin_of_error_percent":0.0,"unemployment_number":0,"margin_of_error_number":12,"total_samples":0,"certainty_ratio":0.0},"25025020303":{"unemployment_percent":42.10526315789473,"margin_of_error_percent":78.94736842105263,"unemployment_number":8,"margin_of_error_number":15,"total_samples":19,"certainty_ratio":0.5333333333333333},"25025030100":{"unemployment_percent":0.0,"margin_of_error_percent":0.0,"unemployment_number":0,"margin_of_error_number":12,"total_samples":0,"certainty_ratio":0.0},"25025030200":{"unemployment_percent":0.0,"margin_of_error_percent":100.0,"unemployment_number":0,"margin_of_error_number":12,"total_samples":12,"certainty_ratio":0.0},"25025030300":{"unemployment_percent":25.766871165644172,"margin_of_error_percent":47.85276073619632,"unemployment_number":42,"margin_of_error_number":78,"total_samples":163,"certainty_ratio":0.5384615384615384},"25025030400":{"unemployment_percent":0.0,"margin_of_error_percent":0.0,"unemployment_number":0,"margin_of_error_number":12,"total_samples":0,"certainty_ratio":0.0},"25025030500":{"unemployment_percent":100.0,"margin_of_error_percent":200.0,"unemployment_number":1,"margin_of_error_number":2,"total_samples":1,"certainty_ratio":0.5},"25025040100":{"unemployment_percent":0.0,"margin_of_error_percent":0.0,"unemployment_number":0,"margin_of_error_number":12,"total_samples":0,"certainty_ratio":0.0},"25025040200":{"unemployment_percent":22.22222222222222,"margin_of_error_percent":33.33333333333333,"unemployment_number":8,"margin_of_error_number":12,"total_samples":36,"certainty_ratio":0.6666666666666666},"25025040300":{"unemployment_percent":0.0,"margin_of_error_percent":20.0,"unemployment_number":0,"margin_of_error_number":12,"total_samples":60,"certainty_ratio":0.0},"25025040401":{"unemployment_percent":0.0,"margin_of_error_percent":13.043478260869565,"unemployment_number":0,"margin_of_error_number":12,"total_samples":92,"certainty_ratio":0.0},"25025040600":{"unemployment_percent":0.0,"margin_of_error_percent":8.391608391608392,"unemployment_number":0,"margin_of_error_number":12,"total_samples":143,"certainty_ratio":0.0},"25025040801":{"unemployment_percent":0.0,"margin_of_error_percent":10.81081081081081,"unemployment_number":0,"margin_of_error_number":12,"total_samples":111,"certainty_ratio":0.0},"25025050101":{"unemployment_percent":0.0,"margin_of_error_percent":53.125,"unemployment_number":0,"margin_of_error_number":17,"total_samples":32,"certainty_ratio":0.0},"25025050200":{"unemployment_percent":0.0,"margin_of_error_percent":26.5625,"unemployment_number":0,"margin_of_error_number":17,"total_samples":64,"certainty_ratio":0.0},"25025050300":{"unemployment_percent":0.0,"margin_of_error_percent":54.54545454545454,"unemployment_number":0,"margin_of_error_number":12,"total_samples":22,"certainty_ratio":0.0},"25025050400":{"unemployment_percent":0.0,"margin_of_error_percent":52.17391304347826,"unemployment_number":0,"margin_of_error_number":12,"total_samples":23,"certainty_ratio":0.0},"25025050500":{"unemployment_percent":0.0,"margin_of_error_percent":57.14285714285714,"unemployment_number":0,"margin_of_error_number":12,"total_samples":21,"certainty_ratio":0.0},"25025050600":{"unemployment_percent":32.5,"margin_of_error_percent":52.5,"unemployment_number":13,"margin_of_error_number":21,"total_samples":40,"certainty_ratio":0.6190476190476191},"25025050700":{"unemployment_percent":0.0,"margin_of_error_percent":113.33333333333333,"unemployment_number":0,"margin_of_error_number":17,"total_samples":15,"certainty_ratio":0.0},"25025050901":{"unemployment_percent":0.0,"margin_of_error_percent":150.0,"unemployment_number":0,"margin_of_error_number":12,"total_samples":8,"certainty_ratio":0.0},"25025051000":{"unemployment_percent":100.0,"margin_of_error_percent":139.1304347826087,"unemployment_number":23,"margin_of_error_number":32,"total_samples":23,"certainty_ratio":0.71875},"25025051101":{"unemployment_percent":0.0,"margin_of_error_percent":9.550561797752808,"unemployment_number":0,"margin_of_error_number":17,"total_samples":178,"certainty_ratio":0.0},"25025051200":{"unemployment_percent":0.0,"margin_of_error_percent":30.0,"unemployment_number":0,"margin_of_error_number":12,"total_samples":40,"certainty_ratio":0.0},"25025060101":{"unemployment_percent":0.0,"margin_of_error_percent":50.0,"unemployment_number":0,"margin_of_error_number":12,"total_samples":24,"certainty_ratio":0.0},"25025060200":{"unemployment_percent":0.0,"margin_of_error_percent":120.0,"unemployment_number":0,"margin_of_error_number":12,"total_samples":10,"certainty_ratio":0.0},"25025060301":{"unemployment_percent":0.0,"margin_of_error_percent":0.0,"unemployment_number":0,"margin_of_error_number":12,"total_samples":0,"certainty_ratio":0.0},"25025060400":{"unemployment_percent":0.0,"margin_of_error_percent":89.47368421052632,"unemployment_number":0,"margin_of_error_number":17,"total_samples":19,"certainty_ratio":0.0},"25025060501":{"unemployment_percent":0.0,"margin_of_error_percent":37.5,"unemployment_number":0,"margin_of_error_number":12,"total_samples":32,"certainty_ratio":0.0},"25025060600":{"unemployment_percent":0.0,"margin_of_error_percent":30.0,"unemployment_number":0,"margin_of_error_number":12,"total_samples":40,"certainty_ratio":0.0},"25025060700":{"unemployment_percent":20.496894409937887,"margin_of_error_percent":18.633540372670808,"unemployment_number":33,"margin_of_error_number":30,"total_samples":161,"certainty_ratio":1.1},"25025060800":{"unemployment_percent":0.0,"margin_of_error_percent":0.0,"unemployment_number":0,"margin_of_error_number":12,"total_samples":0,"certainty_ratio":0.0},"25025061000":{"unemployment_percent":52.071005917159766,"margin_of_error_percent":59.76331360946746,"unemployment_number":88,"margin_of_error_number":101,"total_samples":169,"certainty_ratio":0.8712871287128713},"25025061101":{"unemployment_percent":30.64516129032258,"margin_of_error_percent":28.225806451612907,"unemployment_number":38,"margin_of_error_number":35,"total_samples":124,"certainty_ratio":1.0857142857142856},"25025061200":{"unemployment_percent":0.0,"margin_of_error_percent":50.0,"unemployment_number":0,"margin_of_error_number":12,"total_samples":24,"certainty_ratio":0.0},"25025070101":{"unemployment_percent":22.807017543859647,"margin_of_error_percent":38.59649122807017,"unemployment_number":13,"margin_of_error_number":22,"total_samples":57,"certainty_ratio":0.5909090909090909},"25025070200":{"unemployment_percent":0.0,"margin_of_error_percent":566.6666666666667,"unemployment_number":0,"margin_of_error_number":17,"total_samples":3,"certainty_ratio":0.0},"25025070300":{"unemployment_percent":0.0,"margin_of_error_percent":0.0,"unemployment_number":0,"margin_of_error_number":12,"total_samples":0,"certainty_ratio":0.0},"25025070402":{"unemployment_percent":0.0,"margin_of_error_percent":22.22222222222222,"unemployment_number":0,"margin_of_error_number":12,"total_samples":54,"certainty_ratio":0.0},"25025070500":{"unemployment_percent":0.0,"margin_of_error_percent":9.883720930232558,"unemployment_number":0,"margin_of_error_number":17,"total_samples":172,"certainty_ratio":0.0},"25025070600":{"unemployment_percent":8.333333333333332,"margin_of_error_percent":50.0,"unemployment_number":1,"margin_of_error_number":6,"total_samples":12,"certainty_ratio":0.16666666666666666},"25025070700":{"unemployment_percent":18.64406779661017,"margin_of_error_percent":28.8135593220339,"unemployment_number":11,"margin_of_error_number":17,"total_samples":59,"certainty_ratio":0.6470588235294118},"25025070800":{"unemployment_percent":0.0,"margin_of_error_percent":21.052631578947366,"unemployment_number":0,"margin_of_error_number":12,"total_samples":57,"certainty_ratio":0.0},"25025070900":{"unemployment_percent":39.285714285714285,"margin_of_error_percent":60.71428571428571,"unemployment_number":11,"margin_of_error_number":17,"total_samples":28,"certainty_ratio":0.6470588235294118},"25025071101":{"unemployment_percent":6.504065040650407,"margin_of_error_percent":16.260162601626014,"unemployment_number":8,"margin_of_error_number":20,"total_samples":123,"certainty_ratio":0.4},"25025071201":{"unemployment_percent":23.78048780487805,"margin_of_error_percent":29.268292682926827,"unemployment_number":39,"margin_of_error_number":48,"total_samples":164,"certainty_ratio":0.8125},"25025080100":{"unemployment_percent":17.117117117117118,"margin_of_error_percent":22.52252252252252,"unemployment_number":19,"margin_of_error_number":25,"total_samples":111,"certainty_ratio":0.76},"25025080300":{"unemployment_percent":17.197452229299362,"margin_of_error_percent":17.197452229299362,"unemployment_number":54,"margin_of_error_number":54,"total_samples":314,"certainty_ratio":1.0},"25025080401":{"unemployment_percent":24.45141065830721,"margin_of_error_percent":19.435736677115987,"unemployment_number":78,"margin_of_error_number":62,"total_samples":319,"certainty_ratio":1.2580645161290323},"25025080500":{"unemployment_percent":22.697368421052634,"margin_of_error_percent":15.789473684210526,"unemployment_number":69,"margin_of_error_number":48,"total_samples":304,"certainty_ratio":1.4375},"25025080601":{"unemployment_percent":22.685185185185187,"margin_of_error_percent":21.75925925925926,"unemployment_number":49,"margin_of_error_number":47,"total_samples":216,"certainty_ratio":1.0425531914893618},"25025080801":{"unemployment_percent":12.074303405572756,"margin_of_error_percent":12.074303405572756,"unemployment_number":39,"margin_of_error_number":39,"total_samples":323,"certainty_ratio":1.0},"25025080900":{"unemployment_percent":0.0,"margin_of_error_percent":13.953488372093023,"unemployment_number":0,"margin_of_error_number":12,"total_samples":86,"certainty_ratio":0.0},"25025081001":{"unemployment_percent":16.11111111111111,"margin_of_error_percent":19.72222222222222,"unemployment_number":58,"margin_of_error_number":71,"total_samples":360,"certainty_ratio":0.8169014084507042},"25025081100":{"unemployment_percent":0.0,"margin_of_error_percent":23.076923076923077,"unemployment_number":0,"margin_of_error_number":12,"total_samples":52,"certainty_ratio":0.0},"25025081200":{"unemployment_percent":31.428571428571427,"margin_of_error_percent":30.612244897959183,"unemployment_number":77,"margin_of_error_number":75,"total_samples":245,"certainty_ratio":1.0266666666666666},"25025081300":{"unemployment_percent":19.76401179941003,"margin_of_error_percent":27.728613569321535,"unemployment_number":67,"margin_of_error_number":94,"total_samples":339,"certainty_ratio":0.7127659574468085},"25025081400":{"unemployment_percent":23.125,"margin_of_error_percent":20.625,"unemployment_number":74,"margin_of_error_number":66,"total_samples":320,"certainty_ratio":1.121212121212121},"25025081500":{"unemployment_percent":6.584362139917696,"margin_of_error_percent":10.2880658436214,"unemployment_number":16,"margin_of_error_number":25,"total_samples":243,"certainty_ratio":0.64},"25025081700":{"unemployment_percent":13.003663003663005,"margin_of_error_percent":12.087912087912088,"unemployment_number":71,"margin_of_error_number":66,"total_samples":546,"certainty_ratio":1.0757575757575757},"25025081800":{"unemployment_percent":5.415162454873646,"margin_of_error_percent":7.9422382671480145,"unemployment_number":15,"margin_of_error_number":22,"total_samples":277,"certainty_ratio":0.6818181818181818},"25025081900":{"unemployment_percent":15.301724137931034,"margin_of_error_percent":13.14655172413793,"unemployment_number":71,"margin_of_error_number":61,"total_samples":464,"certainty_ratio":1.1639344262295082},"25025082000":{"unemployment_percent":12.531969309462914,"margin_of_error_percent":9.974424552429667,"unemployment_number":49,"margin_of_error_number":39,"total_samples":391,"certainty_ratio":1.2564102564102564},"25025082100":{"unemployment_percent":1.487603305785124,"margin_of_error_percent":2.644628099173554,"unemployment_number":9,"margin_of_error_number":16,"total_samples":605,"certainty_ratio":0.5625},"25025090100":{"unemployment_percent":11.234396671289876,"margin_of_error_percent":9.43134535367545,"unemployment_number":81,"margin_of_error_number":68,"total_samples":721,"certainty_ratio":1.1911764705882353},"25025090200":{"unemployment_percent":21.428571428571427,"margin_of_error_percent":14.285714285714285,"unemployment_number":84,"margin_of_error_number":56,"total_samples":392,"certainty_ratio":1.5},"25025090300":{"unemployment_percent":16.790123456790123,"margin_of_error_percent":15.308641975308642,"unemployment_number":68,"margin_of_error_number":62,"total_samples":405,"certainty_ratio":1.096774193548387},"25025090400":{"unemployment_percent":23.05593451568895,"margin_of_error_percent":13.915416098226466,"unemployment_number":169,"margin_of_error_number":102,"total_samples":733,"certainty_ratio":1.6568627450980393},"25025090600":{"unemployment_percent":22.295081967213115,"margin_of_error_percent":13.442622950819672,"unemployment_number":136,"margin_of_error_number":82,"total_samples":610,"certainty_ratio":1.6585365853658536},"25025090700":{"unemployment_percent":40.44943820224719,"margin_of_error_percent":53.93258426966292,"unemployment_number":36,"margin_of_error_number":48,"total_samples":89,"certainty_ratio":0.75},"25025090901":{"unemployment_percent":18.91891891891892,"margin_of_error_percent":24.324324324324326,"unemployment_number":14,"margin_of_error_number":18,"total_samples":74,"certainty_ratio":0.7777777777777778},"25025091001":{"unemployment_percent":0.0,"margin_of_error_percent":5.9405940594059405,"unemployment_number":0,"margin_of_error_number":12,"total_samples":202,"certainty_ratio":0.0},"25025091100":{"unemployment_percent":0.0,"margin_of_error_percent":11.428571428571429,"unemployment_number":0,"margin_of_error_number":12,"total_samples":105,"certainty_ratio":0.0},"25025091200":{"unemployment_percent":2.898550724637681,"margin_of_error_percent":7.246376811594203,"unemployment_number":10,"margin_of_error_number":25,"total_samples":345,"certainty_ratio":0.4},"25025091300":{"unemployment_percent":6.150341685649203,"margin_of_error_percent":6.83371298405467,"unemployment_number":27,"margin_of_error_number":30,"total_samples":439,"certainty_ratio":0.9},"25025091400":{"unemployment_percent":13.348946135831383,"margin_of_error_percent":13.583138173302109,"unemployment_number":57,"margin_of_error_number":58,"total_samples":427,"certainty_ratio":0.9827586206896551},"25025091500":{"unemployment_percent":21.182266009852217,"margin_of_error_percent":13.30049261083744,"unemployment_number":129,"margin_of_error_number":81,"total_samples":609,"certainty_ratio":1.5925925925925926},"25025091600":{"unemployment_percent":0.0,"margin_of_error_percent":4.669260700389105,"unemployment_number":0,"margin_of_error_number":12,"total_samples":257,"certainty_ratio":0.0},"25025091700":{"unemployment_percent":10.176125244618394,"margin_of_error_percent":7.632093933463796,"unemployment_number":52,"margin_of_error_number":39,"total_samples":511,"certainty_ratio":1.3333333333333333},"25025091800":{"unemployment_percent":10.152284263959391,"margin_of_error_percent":13.705583756345177,"unemployment_number":40,"margin_of_error_number":54,"total_samples":394,"certainty_ratio":0.7407407407407407},"25025091900":{"unemployment_percent":9.333333333333334,"margin_of_error_percent":6.666666666666667,"unemployment_number":63,"margin_of_error_number":45,"total_samples":675,"certainty_ratio":1.4},"25025092000":{"unemployment_percent":18.22721598002497,"margin_of_error_percent":11.235955056179774,"unemployment_number":146,"margin_of_error_number":90,"total_samples":801,"certainty_ratio":1.6222222222222222},"25025092101":{"unemployment_percent":3.1963470319634704,"margin_of_error_percent":4.794520547945205,"unemployment_number":14,"margin_of_error_number":21,"total_samples":438,"certainty_ratio":0.6666666666666666},"25025092200":{"unemployment_percent":9.35483870967742,"margin_of_error_percent":12.258064516129032,"unemployment_number":29,"margin_of_error_number":38,"total_samples":310,"certainty_ratio":0.7631578947368421},"25025092300":{"unemployment_percent":7.731958762886598,"margin_of_error_percent":5.154639175257731,"unemployment_number":45,"margin_of_error_number":30,"total_samples":582,"certainty_ratio":1.5},"25025092400":{"unemployment_percent":4.327375352775165,"margin_of_error_percent":5.174035747883349,"unemployment_number":46,"margin_of_error_number":55,"total_samples":1063,"certainty_ratio":0.8363636363636363},"25025100100":{"unemployment_percent":7.643884892086331,"margin_of_error_percent":5.215827338129497,"unemployment_number":85,"margin_of_error_number":58,"total_samples":1112,"certainty_ratio":1.4655172413793103},"25025100200":{"unemployment_percent":22.62295081967213,"margin_of_error_percent":10.655737704918032,"unemployment_number":138,"margin_of_error_number":65,"total_samples":610,"certainty_ratio":2.123076923076923},"25025100300":{"unemployment_percent":6.6473988439306355,"margin_of_error_percent":6.791907514450866,"unemployment_number":46,"margin_of_error_number":47,"total_samples":692,"certainty_ratio":0.9787234042553191},"25025100400":{"unemployment_percent":7.2992700729927,"margin_of_error_percent":6.715328467153285,"unemployment_number":50,"margin_of_error_number":46,"total_samples":685,"certainty_ratio":1.0869565217391304},"25025100500":{"unemployment_percent":26.32794457274827,"margin_of_error_percent":15.819861431870669,"unemployment_number":228,"margin_of_error_number":137,"total_samples":866,"certainty_ratio":1.6642335766423357},"25025100601":{"unemployment_percent":0.0,"margin_of_error_percent":2.607361963190184,"unemployment_number":0,"margin_of_error_number":17,"total_samples":652,"certainty_ratio":0.0},"25025100603":{"unemployment_percent":0.0,"margin_of_error_percent":25.53191489361702,"unemployment_number":0,"margin_of_error_number":12,"total_samples":47,"certainty_ratio":0.0},"25025100700":{"unemployment_percent":0.0,"margin_of_error_percent":92.3076923076923,"unemployment_number":0,"margin_of_error_number":12,"total_samples":13,"certainty_ratio":0.0},"25025100800":{"unemployment_percent":6.988352745424292,"margin_of_error_percent":9.317803660565724,"unemployment_number":42,"margin_of_error_number":56,"total_samples":601,"certainty_ratio":0.75},"25025100900":{"unemployment_percent":19.5822454308094,"margin_of_error_percent":12.010443864229766,"unemployment_number":150,"margin_of_error_number":92,"total_samples":766,"certainty_ratio":1.6304347826086956},"25025101001":{"unemployment_percent":5.08100147275405,"margin_of_error_percent":5.596465390279824,"unemployment_number":69,"margin_of_error_number":76,"total_samples":1358,"certainty_ratio":0.9078947368421053},"25025101002":{"unemployment_percent":15.525876460767945,"margin_of_error_percent":12.020033388981636,"unemployment_number":186,"margin_of_error_number":144,"total_samples":1198,"certainty_ratio":1.2916666666666667},"25025101101":{"unemployment_percent":14.173228346456693,"margin_of_error_percent":9.186351706036746,"unemployment_number":108,"margin_of_error_number":70,"total_samples":762,"certainty_ratio":1.542857142857143},"25025101102":{"unemployment_percent":8.780903665814153,"margin_of_error_percent":6.138107416879795,"unemployment_number":103,"margin_of_error_number":72,"total_samples":1173,"certainty_ratio":1.4305555555555556},"25025110103":{"unemployment_percent":20.224719101123593,"margin_of_error_percent":14.125200642054574,"unemployment_number":126,"margin_of_error_number":88,"total_samples":623,"certainty_ratio":1.4318181818181819},"25025110201":{"unemployment_percent":4.184100418410042,"margin_of_error_percent":7.112970711297072,"unemployment_number":10,"margin_of_error_number":17,"total_samples":239,"certainty_ratio":0.5882352941176471},"25025110301":{"unemployment_percent":0.0,"margin_of_error_percent":4.511278195488721,"unemployment_number":0,"margin_of_error_number":12,"total_samples":266,"certainty_ratio":0.0},"25025110401":{"unemployment_percent":15.312500000000002,"margin_of_error_percent":17.1875,"unemployment_number":49,"margin_of_error_number":55,"total_samples":320,"certainty_ratio":0.8909090909090909},"25025110403":{"unemployment_percent":0.0,"margin_of_error_percent":3.4782608695652173,"unemployment_number":0,"margin_of_error_number":12,"total_samples":345,"certainty_ratio":0.0},"25025110501":{"unemployment_percent":0.0,"margin_of_error_percent":80.0,"unemployment_number":0,"margin_of_error_number":12,"total_samples":15,"certainty_ratio":0.0},"25025110502":{"unemployment_percent":0.0,"margin_of_error_percent":7.894736842105263,"unemployment_number":0,"margin_of_error_number":12,"total_samples":152,"certainty_ratio":0.0},"25025110601":{"unemployment_percent":0.0,"margin_of_error_percent":109.09090909090908,"unemployment_number":0,"margin_of_error_number":12,"total_samples":11,"certainty_ratio":0.0},"25025110607":{"unemployment_percent":3.6363636363636362,"margin_of_error_percent":7.2727272727272725,"unemployment_number":2,"margin_of_error_number":4,"total_samples":55,"certainty_ratio":0.5},"25025120103":{"unemployment_percent":0.0,"margin_of_error_percent":52.17391304347826,"unemployment_number":0,"margin_of_error_number":12,"total_samples":23,"certainty_ratio":0.0},"25025120104":{"unemployment_percent":65.0,"margin_of_error_percent":82.5,"unemployment_number":26,"margin_of_error_number":33,"total_samples":40,"certainty_ratio":0.7878787878787878},"25025120105":{"unemployment_percent":0.0,"margin_of_error_percent":38.70967741935484,"unemployment_number":0,"margin_of_error_number":12,"total_samples":31,"certainty_ratio":0.0},"25025120201":{"unemployment_percent":3.9525691699604746,"margin_of_error_percent":6.719367588932807,"unemployment_number":10,"margin_of_error_number":17,"total_samples":253,"certainty_ratio":0.5882352941176471},"25025120301":{"unemployment_percent":0.0,"margin_of_error_percent":4.722222222222222,"unemployment_number":0,"margin_of_error_number":17,"total_samples":360,"certainty_ratio":0.0},"25025120400":{"unemployment_percent":18.29268292682927,"margin_of_error_percent":30.48780487804878,"unemployment_number":30,"margin_of_error_number":50,"total_samples":164,"certainty_ratio":0.6},"25025120500":{"unemployment_percent":0.0,"margin_of_error_percent":23.076923076923077,"unemployment_number":0,"margin_of_error_number":12,"total_samples":52,"certainty_ratio":0.0},"25025120600":{"unemployment_percent":0.0,"margin_of_error_percent":10.526315789473683,"unemployment_number":0,"margin_of_error_number":12,"total_samples":114,"certainty_ratio":0.0},"25025120700":{"unemployment_percent":0.0,"margin_of_error_percent":26.666666666666668,"unemployment_number":0,"margin_of_error_number":12,"total_samples":45,"certainty_ratio":0.0},"25025130100":{"unemployment_percent":0.0,"margin_of_error_percent":14.782608695652174,"unemployment_number":0,"margin_of_error_number":17,"total_samples":115,"certainty_ratio":0.0},"25025130200":{"unemployment_percent":0.0,"margin_of_error_percent":60.71428571428571,"unemployment_number":0,"margin_of_error_number":17,"total_samples":28,"certainty_ratio":0.0},"25025130300":{"unemployment_percent":0.0,"margin_of_error_percent":22.22222222222222,"unemployment_number":0,"margin_of_error_number":12,"total_samples":54,"certainty_ratio":0.0},"25025130402":{"unemployment_percent":0.0,"margin_of_error_percent":80.0,"unemployment_number":0,"margin_of_error_number":12,"total_samples":15,"certainty_ratio":0.0},"25025130404":{"unemployment_percent":0.0,"margin_of_error_percent":6.122448979591836,"unemployment_number":0,"margin_of_error_number":12,"total_samples":196,"certainty_ratio":0.0},"25025130406":{"unemployment_percent":4.813664596273292,"margin_of_error_percent":6.987577639751552,"unemployment_number":31,"margin_of_error_number":45,"total_samples":644,"certainty_ratio":0.6888888888888889},"25025140102":{"unemployment_percent":21.766561514195583,"margin_of_error_percent":13.564668769716087,"unemployment_number":138,"margin_of_error_number":86,"total_samples":634,"certainty_ratio":1.6046511627906976},"25025140105":{"unemployment_percent":2.8455284552845526,"margin_of_error_percent":4.878048780487805,"unemployment_number":14,"margin_of_error_number":24,"total_samples":492,"certainty_ratio":0.5833333333333334},"25025140106":{"unemployment_percent":18.53035143769968,"margin_of_error_percent":14.376996805111823,"unemployment_number":58,"margin_of_error_number":45,"total_samples":313,"certainty_ratio":1.288888888888889},"25025140107":{"unemployment_percent":15.019762845849801,"margin_of_error_percent":13.83399209486166,"unemployment_number":38,"margin_of_error_number":35,"total_samples":253,"certainty_ratio":1.0857142857142856},"25025140201":{"unemployment_percent":12.88135593220339,"margin_of_error_percent":12.54237288135593,"unemployment_number":38,"margin_of_error_number":37,"total_samples":295,"certainty_ratio":1.027027027027027},"25025140202":{"unemployment_percent":16.415410385259634,"margin_of_error_percent":13.23283082077052,"unemployment_number":98,"margin_of_error_number":79,"total_samples":597,"certainty_ratio":1.240506329113924},"25025140300":{"unemployment_percent":28.257790368271955,"margin_of_error_percent":13.739376770538245,"unemployment_number":399,"margin_of_error_number":194,"total_samples":1412,"certainty_ratio":2.056701030927835},"25025140400":{"unemployment_percent":10.199004975124378,"margin_of_error_percent":8.955223880597014,"unemployment_number":164,"margin_of_error_number":144,"total_samples":1608,"certainty_ratio":1.1388888888888888},"25025160101":{"unemployment_percent":0.684931506849315,"margin_of_error_percent":3.4246575342465753,"unemployment_number":1,"margin_of_error_number":5,"total_samples":146,"certainty_ratio":0.2},"25025160200":{"unemployment_percent":0.0,"margin_of_error_percent":0.0,"unemployment_number":0,"margin_of_error_number":12,"total_samples":0,"certainty_ratio":0.0},"25025160300":{"unemployment_percent":12.698412698412698,"margin_of_error_percent":20.634920634920633,"unemployment_number":8,"margin_of_error_number":13,"total_samples":63,"certainty_ratio":0.6153846153846154},"25025160400":{"unemployment_percent":0.0,"margin_of_error_percent":18.181818181818183,"unemployment_number":0,"margin_of_error_number":12,"total_samples":66,"certainty_ratio":0.0},"25025160501":{"unemployment_percent":31.25,"margin_of_error_percent":50.0,"unemployment_number":15,"margin_of_error_number":24,"total_samples":48,"certainty_ratio":0.625},"25025160502":{"unemployment_percent":18.902439024390244,"margin_of_error_percent":31.097560975609756,"unemployment_number":31,"margin_of_error_number":51,"total_samples":164,"certainty_ratio":0.6078431372549019},"25025160601":{"unemployment_percent":0.0,"margin_of_error_percent":15.0,"unemployment_number":0,"margin_of_error_number":12,"total_samples":80,"certainty_ratio":0.0},"25025160602":{"unemployment_percent":0.0,"margin_of_error_percent":9.941520467836257,"unemployment_number":0,"margin_of_error_number":17,"total_samples":171,"certainty_ratio":0.0},"25025170100":{"unemployment_percent":0.0,"margin_of_error_percent":10.240963855421686,"unemployment_number":0,"margin_of_error_number":17,"total_samples":166,"certainty_ratio":0.0},"25025170200":{"unemployment_percent":0.0,"margin_of_error_percent":13.793103448275861,"unemployment_number":0,"margin_of_error_number":12,"total_samples":87,"certainty_ratio":0.0},"25025170300":{"unemployment_percent":9.67741935483871,"margin_of_error_percent":16.129032258064516,"unemployment_number":21,"margin_of_error_number":35,"total_samples":217,"certainty_ratio":0.6},"25025170400":{"unemployment_percent":34.5679012345679,"margin_of_error_percent":53.70370370370371,"unemployment_number":56,"margin_of_error_number":87,"total_samples":162,"certainty_ratio":0.6436781609195402},"25025170501":{"unemployment_percent":0.0,"margin_of_error_percent":18.461538461538463,"unemployment_number":0,"margin_of_error_number":12,"total_samples":65,"certainty_ratio":0.0},"25025170502":{"unemployment_percent":0.0,"margin_of_error_percent":0.0,"unemployment_number":0,"margin_of_error_number":12,"total_samples":0,"certainty_ratio":0.0},"25025170601":{"unemployment_percent":0.0,"margin_of_error_percent":17.346938775510203,"unemployment_number":0,"margin_of_error_number":17,"total_samples":98,"certainty_ratio":0.0},"25025170701":{"unemployment_percent":0.0,"margin_of_error_percent":40.0,"unemployment_number":0,"margin_of_error_number":12,"total_samples":30,"certainty_ratio":0.0},"25025170702":{"unemployment_percent":30.714285714285715,"margin_of_error_percent":48.57142857142857,"unemployment_number":43,"margin_of_error_number":68,"total_samples":140,"certainty_ratio":0.6323529411764706},"25025170800":{"unemployment_percent":0.0,"margin_of_error_percent":80.95238095238095,"unemployment_number":0,"margin_of_error_number":17,"total_samples":21,"certainty_ratio":0.0},"25025180101":{"unemployment_percent":0.0,"margin_of_error_percent":57.14285714285714,"unemployment_number":0,"margin_of_error_number":12,"total_samples":21,"certainty_ratio":0.0},"25025180200":{"unemployment_percent":0.0,"margin_of_error_percent":30.0,"unemployment_number":0,"margin_of_error_number":12,"total_samples":40,"certainty_ratio":0.0},"25025180301":{"unemployment_percent":0.0,"margin_of_error_percent":75.0,"unemployment_number":0,"margin_of_error_number":12,"total_samples":16,"certainty_ratio":0.0},"25025180400":{"unemployment_percent":0.0,"margin_of_error_percent":33.33333333333333,"unemployment_number":0,"margin_of_error_number":12,"total_samples":36,"certainty_ratio":0.0},"25025180500":{"unemployment_percent":0.0,"margin_of_error_percent":100.0,"unemployment_number":0,"margin_of_error_number":12,"total_samples":12,"certainty_ratio":0.0},"25025980101":{"unemployment_percent":0.0,"margin_of_error_percent":22.641509433962266,"unemployment_number":0,"margin_of_error_number":12,"total_samples":53,"certainty_ratio":0.0},"25025980300":{"unemployment_percent":100.0,"margin_of_error_percent":235.71428571428572,"unemployment_number":14,"margin_of_error_number":33,"total_samples":14,"certainty_ratio":0.42424242424242425},"25025980700":{"unemployment_percent":0.0,"margin_of_error_percent":0.0,"unemployment_number":0,"margin_of_error_number":12,"total_samples":0,"certainty_ratio":0.0},"25025981000":{"unemployment_percent":0.0,"margin_of_error_percent":0.0,"unemployment_number":0,"margin_of_error_number":12,"total_samples":0,"certainty_ratio":0.0},"25025981100":{"unemployment_percent":0.0,"margin_of_error_percent":48.0,"unemployment_number":0,"margin_of_error_number":12,"total_samples":25,"certainty_ratio":0.0},"25025981201":{"unemployment_percent":0.0,"margin_of_error_percent":0.0,"unemployment_number":0,"margin_of_error_number":12,"total_samples":0,"certainty_ratio":0.0},"25025981202":{"unemployment_percent":0.0,"margin_of_error_percent":0.0,"unemployment_number":0,"margin_of_error_number":12,"total_samples":0,"certainty_ratio":0.0},"25025981300":{"unemployment_percent":0.0,"margin_of_error_percent":171.42857142857142,"unemployment_number":0,"margin_of_error_number":12,"total_samples":7,"certainty_ratio":0.0},"25025981501":{"unemployment_percent":0.0,"margin_of_error_percent":0.0,"unemployment_number":0,"margin_of_error_number":12,"total_samples":0,"certainty_ratio":0.0},"25025981502":{"unemployment_percent":0.0,"margin_of_error_percent":0.0,"unemployment_number":0,"margin_of_error_number":12,"total_samples":0,"certainty_ratio":0.0},"25025981600":{"unemployment_percent":0.0,"margin_of_error_percent":0.0,"unemployment_number":0,"margin_of_error_number":12,"total_samples":0,"certainty_ratio":0.0},"25025981700":{"unemployment_percent":0.0,"margin_of_error_percent":0.0,"unemployment_number":0,"margin_of_error_number":12,"total_samples":0,"certainty_ratio":0.0},"25025981800":{"unemployment_percent":0.0,"margin_of_error_percent":0.0,"unemployment_number":0,"margin_of_error_number":12,"total_samples":0,"certainty_ratio":0.0},"25025990101":{"unemployment_percent":0.0,"margin_of_error_percent":66.66666666666666,"unemployment_number":0,"margin_of_error_number":12,"total_samples":18,"certainty_ratio":0.0}}}